piroattack/.version
piroattack/__init__.py
piroattack/main.py
piroattack/piroattack.py
piroattack/res/lists/useragents/android.txt
piroattack/res/lists/useragents/browsers.txt
piroattack/res/lists/useragents/cloudplatforms.txt
piroattack/res/lists/useragents/crawlers.txt
piroattack/res/lists/useragents/feedreaders.txt
piroattack/res/lists/useragents/ipad.txt
piroattack/res/lists/useragents/iphone.txt
piroattack/res/lists/useragents/libraries.txt
piroattack/res/lists/useragents/linkcheckers.txt
piroattack/res/lists/useragents/others.txt
piroattack/res/lists/useragents/validators.txt
piroattack/res/lists/useragents/zytrax-browserid.txt
piroattack/util/getuas.py
piroattack-0.0.1.dist-info/LICENSE
piroattack-0.0.1.dist-info/METADATA
piroattack-0.0.1.dist-info/WHEEL
piroattack-0.0.1.dist-info/entry_points.txt
piroattack-0.0.1.dist-info/top_level.txt
piroattack-0.0.1.dist-info/RECORD
