Metadata-Version: 2.1
Name: piroattack
Version: 0.0.1
Summary: PiroAttack - A Python 3 app for SECURITY TESTING PURPOSES ONLY!
Home-page: https://github.com/hk4crprasad/piroattack
Download-URL: https://github.com/hk4crprasad/piroattack/archive/pypi.zip
Author: HK4CRPRASAD
Author-email: hotahara12@gmail.com
License: GPL-3.0
Keywords: ddos,attack,multi-ddos,piro,hk4crprasad,piroattack
Classifier: Development Status :: 4 - Beta
Classifier: Intended Audience :: Developers
Classifier: Topic :: Software Development :: Libraries :: Python Modules
Classifier: License :: OSI Approved :: GNU General Public License v3 (GPLv3)
Classifier: Programming Language :: Python :: 3
Classifier: Programming Language :: Python :: 3.6
Classifier: Programming Language :: Python :: 3.7
Classifier: Programming Language :: Python :: 3.8
Classifier: Programming Language :: Python :: 3.9
Classifier: Programming Language :: Python :: 3.10
Classifier: Programming Language :: Python :: 3.11
Classifier: Operating System :: OS Independent
Classifier: Topic :: Communications :: Chat
Requires-Python: >=3.6
License-File: LICENSE
Requires-Dist: rich
Requires-Dist: requests
Requires-Dist: beautifulsoup4
